<report xmlns="http://developer.cognos.com/schemas/report/8.0/" useStyleVersion="10" expressionLocale="en-us">
	<modelPath>/content/package[@name='Everything Package']/model[@name='2014-01-30T15:17:47.468Z']</modelPath>
	<drillBehavior modelBasedDrillThru="true"/>
	<queries>
		<query name="Race Query">
			<source>
				<model/>
			</source>
			<selection><dataItem name="ID Number" aggregate="none" rollupAggregate="none"><expression>[General Information].[Profile].[ID Number]</expression><XMLAttributes><XMLAttribute name="RS_dataType" value="1" output="no"/><XMLAttribute name="RS_dataUsage" value="identifier" output="no"/></XMLAttributes></dataItem><dataItem name="Full Name" aggregate="none" rollupAggregate="none"><expression>[General Information].[Profile].[Full Name]</expression><XMLAttributes><XMLAttribute name="RS_dataType" value="3" output="no"/><XMLAttribute name="RS_dataUsage" value="identifier" output="no"/></XMLAttributes></dataItem><dataItem name="Race Code" aggregate="none" rollupAggregate="none"><expression>[General Information].[Profile].[Ethnic Code (New)]</expression><XMLAttributes><XMLAttribute name="RS_dataType" value="3" output="no"/><XMLAttribute name="RS_dataUsage" value="attribute" output="no"/></XMLAttributes></dataItem><dataItemListSummary refDataItem="ID Number" aggregateMethod="countDistinct" name="Count Distinct(ID Number)"/><dataItem name="Ethnic Code" aggregate="none" rollupAggregate="none"><expression>[General Information].[Profile].[Ethnic Code]</expression><XMLAttributes><XMLAttribute name="RS_dataType" value="3" output="no"/><XMLAttribute name="RS_dataUsage" value="attribute" output="no"/></XMLAttributes></dataItem><dataItem name="Office Added By Code" aggregate="none" rollupAggregate="none"><expression>[General Information].[Name and Address].[Office Added By Code]</expression><XMLAttributes><XMLAttribute name="RS_dataType" value="3" output="no"/><XMLAttribute name="RS_dataUsage" value="attribute" output="no"/></XMLAttributes></dataItem></selection>
			<detailFilters><detailFilter use="required" postAutoAggregation="false"><filterDefinition><filterInValues refDataItem="Race Code" dataType="string"><filterValues><filterValue>
								</filterValue></filterValues></filterInValues></filterDefinition></detailFilter></detailFilters></query>
		<query name="Title Query"><source><model/></source><selection><dataItem name="ID Number" aggregate="none" rollupAggregate="none"><expression>[General Information].[Profile].[ID Number]</expression><XMLAttributes><XMLAttribute name="RS_dataType" value="1" output="no"/><XMLAttribute name="RS_dataUsage" value="identifier" output="no"/></XMLAttributes></dataItem><dataItem name="Full Name" aggregate="none" rollupAggregate="none"><expression>[General Information].[Profile].[Full Name]</expression><XMLAttributes><XMLAttribute name="RS_dataType" value="3" output="no"/><XMLAttribute name="RS_dataUsage" value="identifier" output="no"/></XMLAttributes></dataItem><dataItem name="Title Code" aggregate="none" rollupAggregate="none"><expression>[General Information].[Name and Address].[Title Code]</expression><XMLAttributes><XMLAttribute name="RS_dataType" value="3" output="no"/><XMLAttribute name="RS_dataUsage" value="attribute" output="no"/></XMLAttributes></dataItem><dataItem name="Gender Code" aggregate="none" rollupAggregate="none"><expression>[General Information].[Profile].[Gender Code]</expression><XMLAttributes><XMLAttribute name="RS_dataType" value="3" output="no"/><XMLAttribute name="RS_dataUsage" value="attribute" output="no"/></XMLAttributes></dataItem><dataItemListSummary refDataItem="ID Number" aggregateMethod="countDistinct" name="Count Distinct(ID Number)"/><dataItem name="Office Added By Code" aggregate="none" rollupAggregate="none"><expression>[General Information].[Name and Address].[Office Added By Code]</expression><XMLAttributes><XMLAttribute name="RS_dataType" value="3" output="no"/><XMLAttribute name="RS_dataUsage" value="attribute" output="no"/></XMLAttributes></dataItem></selection><detailFilters><detailFilter use="required" postAutoAggregation="false"><filterExpression>([Title Code] in ('MISS', 'MRS', 'MS') AND [Gender Code] = 'M' )OR ([Title Code] in ('BR', 'FA', 'MR') AND [Gender Code] = 'F' )</filterExpression></detailFilter></detailFilters></query><query name="Married Title Query"><source><model/></source><selection><dataItem name="ID Number" aggregate="none" rollupAggregate="none"><expression>[General Information].[Profile].[ID Number]</expression><XMLAttributes><XMLAttribute name="RS_dataType" value="1" output="no"/><XMLAttribute name="RS_dataUsage" value="identifier" output="no"/></XMLAttributes></dataItem><dataItem name="Full Name" aggregate="none" rollupAggregate="none"><expression>[General Information].[Profile].[Full Name]</expression><XMLAttributes><XMLAttribute name="RS_dataType" value="3" output="no"/><XMLAttribute name="RS_dataUsage" value="identifier" output="no"/></XMLAttributes></dataItem><dataItem name="Marital Status Code" aggregate="none" rollupAggregate="none"><expression>[General Information].[Profile].[Marital Status Code]</expression><XMLAttributes><XMLAttribute name="RS_dataType" value="3" output="no"/><XMLAttribute name="RS_dataUsage" value="attribute" output="no"/></XMLAttributes></dataItem><dataItem name="Title Code" aggregate="none" rollupAggregate="none"><expression>[General Information].[Name and Address].[Title Code]</expression><XMLAttributes><XMLAttribute name="RS_dataType" value="3" output="no"/><XMLAttribute name="RS_dataUsage" value="attribute" output="no"/></XMLAttributes></dataItem><dataItem name="Relationship Code" aggregate="none" rollupAggregate="none"><expression>[General Information].[Relationships].[Relationship Code]</expression><XMLAttributes><XMLAttribute name="RS_dataType" value="3" output="no"/><XMLAttribute name="RS_dataUsage" value="attribute" output="no"/></XMLAttributes></dataItem><dataItem name="Relation ID Number" aggregate="none" rollupAggregate="none"><expression>[General Information].[Relationships].[Relation ID Number]</expression><XMLAttributes><XMLAttribute name="RS_dataType" value="1" output="no"/><XMLAttribute name="RS_dataUsage" value="identifier" output="no"/></XMLAttributes></dataItem><dataItem name="Primary ID Number" aggregate="none" rollupAggregate="none"><expression>[General Information].[Relationships].[Primary ID Number]</expression><XMLAttributes><XMLAttribute name="RS_dataType" value="1" output="no"/><XMLAttribute name="RS_dataUsage" value="identifier" output="no"/></XMLAttributes></dataItem><dataItem name="Primary Name" aggregate="none" rollupAggregate="none"><expression>[General Information].[Relationships].[Primary Name]</expression><XMLAttributes><XMLAttribute name="RS_dataType" value="3" output="no"/><XMLAttribute name="RS_dataUsage" value="identifier" output="no"/></XMLAttributes></dataItem><dataItemListSummary refDataItem="ID Number" aggregateMethod="countDistinct" name="Count Distinct(ID Number)"/><dataItem name="Office Added By Code" aggregate="none" rollupAggregate="none"><expression>[General Information].[Name and Address].[Office Added By Code]</expression><XMLAttributes><XMLAttribute name="RS_dataType" value="3" output="no"/><XMLAttribute name="RS_dataUsage" value="attribute" output="no"/></XMLAttributes></dataItem></selection><detailFilters><detailFilter use="required" postAutoAggregation="false"><filterExpression>([Marital Status Code] in ('S', '', ' ') AND [Title Code] = 'MRS') OR ([Marital Status Code] = 'M' AND [Title Code] = 'MISS')</filterExpression></detailFilter><detailFilter use="required" postAutoAggregation="false"><filterDefinition><filterInValues refDataItem="Relationship Code" dataType="string"><filterValues><filterValue>HW  </filterValue><filterValue>SPSE</filterValue><filterValue>
								</filterValue></filterValues></filterInValues></filterDefinition></detailFilter></detailFilters></query><query name="Cell Phone Query"><source><model/></source><selection><dataItem name="ID Number" aggregate="none" rollupAggregate="none"><expression>[General Information].[Name and Address].[ID Number]</expression><XMLAttributes><XMLAttribute name="RS_dataType" value="1" output="no"/><XMLAttribute name="RS_dataUsage" value="identifier" output="no"/></XMLAttributes></dataItem><dataItem name="Full Name (Last, First)" aggregate="none" rollupAggregate="none"><expression>[General Information].[Name and Address].[Full Name (Last, First)]</expression><XMLAttributes><XMLAttribute name="RS_dataType" value="3" output="no"/><XMLAttribute name="RS_dataUsage" value="identifier" output="no"/></XMLAttributes></dataItem><dataItem name="Phone Number" aggregate="none" rollupAggregate="none"><expression>[General Information].[Name and Address].[Phone Number]</expression><XMLAttributes><XMLAttribute name="RS_dataType" value="3" output="no"/><XMLAttribute name="RS_dataUsage" value="attribute" output="no"/></XMLAttributes></dataItem><dataItem name="AA Code" aggregate="none" rollupAggregate="none"><expression>[General Information].[Alternate Addresses].[AA Code]</expression><XMLAttributes><XMLAttribute name="RS_dataType" value="3" output="no"/><XMLAttribute name="RS_dataUsage" value="identifier" output="no"/></XMLAttributes></dataItem><dataItem name="AA Phone Number" aggregate="none" rollupAggregate="none"><expression>[General Information].[Alternate Addresses].[AA Phone Number]</expression><XMLAttributes><XMLAttribute name="RS_dataType" value="3" output="no"/><XMLAttribute name="RS_dataUsage" value="attribute" output="no"/></XMLAttributes></dataItem><dataItemListSummary refDataItem="ID Number" aggregateMethod="countDistinct" name="Count Distinct(ID Number)"/><dataItem name="Office Added By Code" aggregate="none" rollupAggregate="none"><expression>[General Information].[Name and Address].[Office Added By Code]</expression><XMLAttributes><XMLAttribute name="RS_dataType" value="3" output="no"/><XMLAttribute name="RS_dataUsage" value="attribute" output="no"/></XMLAttributes></dataItem></selection><detailFilters><detailFilter use="required" postAutoAggregation="false"><filterExpression>[Phone Number] = [AA Phone Number]</filterExpression></detailFilter><detailFilter use="required" postAutoAggregation="false"><filterDefinition><filterInValues refDataItem="AA Code" dataType="string"><filterValues><filterValue>CELL</filterValue></filterValues></filterInValues></filterDefinition></detailFilter></detailFilters></query><query name="IDR Profile Query">
			<source>
				<sqlQuery name="SQL1" dataSource="CX">
					<sqlText>select id from profile_rec</sqlText>
					<mdProjectedItems><mdProjectedItem name="id"/></mdProjectedItems></sqlQuery></source>
			<selection><dataItem name="id"><expression>[SQL1].[id]</expression></dataItem></selection>
		</query><query name="IDR Bus Query">
			<source>
				<sqlQuery name="SQL2" dataSource="CX">
					<sqlText>select id from bus_rec</sqlText>
					<mdProjectedItems><mdProjectedItem name="id"/></mdProjectedItems></sqlQuery></source>
			<selection><dataItem name="id"><expression>[SQL2].[id]</expression></dataItem></selection>
		</query><query name="IDR Org Query">
			<source>
				<sqlQuery name="SQL3" dataSource="CX">
					<sqlText>select id from org_rec</sqlText>
					<mdProjectedItems><mdProjectedItem name="id"/></mdProjectedItems></sqlQuery></source>
			<selection><dataItem name="id"><expression>[SQL3].[id]</expression></dataItem></selection>
		</query><query name="IDR Church Query">
			<source>
				<sqlQuery name="SQL4" dataSource="CX">
					<sqlText>select id from church_rec</sqlText>
					<mdProjectedItems><mdProjectedItem name="id"/></mdProjectedItems></sqlQuery></source>
			<selection><dataItem name="id"><expression>[SQL4].[id]</expression></dataItem></selection>
		</query><query name="IDR Foundation Query">
			<source>
				<sqlQuery name="SQL5" dataSource="CX">
					<sqlText>select id from fnd_rec</sqlText>
					<mdProjectedItems><mdProjectedItem name="id"/></mdProjectedItems></sqlQuery></source>
			<selection><dataItem name="id"><expression>[SQL5].[id]</expression></dataItem></selection>
		</query><query name="IDR School Query">
			<source>
				<sqlQuery name="SQL6" dataSource="CX">
					<sqlText>select id from sch_rec</sqlText>
					<mdProjectedItems><mdProjectedItem name="id"/></mdProjectedItems></sqlQuery></source>
			<selection><dataItem name="id"><expression>[SQL6].[id]</expression></dataItem></selection>
		</query><query name="Identifying Records Query"><source><model/></source><selection><dataItem name="ID Number" aggregate="none" rollupAggregate="none"><expression>[General Information].[Name and Address].[ID Number]</expression><XMLAttributes><XMLAttribute name="RS_dataType" value="1" output="no"/><XMLAttribute name="RS_dataUsage" value="identifier" output="no"/></XMLAttributes></dataItem><dataItem name="Full Name (Last, First)" aggregate="none" rollupAggregate="none"><expression>[General Information].[Name and Address].[Full Name (Last, First)]</expression><XMLAttributes><XMLAttribute name="RS_dataType" value="3" output="no"/><XMLAttribute name="RS_dataUsage" value="identifier" output="no"/></XMLAttributes></dataItem><dataItem name="Person"><expression>if ([ID Number] in ([IDR Profile Query].[id]))
then (1)
else (0)</expression></dataItem><dataItem name="Business"><expression>if ([ID Number] in ([IDR Bus Query].[id]))
then (1)
else (0)</expression></dataItem><dataItem name="Organization"><expression>if ([ID Number] in ([IDR Org Query].[id]))
then (1)
else (0)</expression></dataItem><dataItem name="Church"><expression>if ([ID Number] in ([IDR Church Query].[id]))
then (1)
else (0)</expression></dataItem><dataItem name="Foundation"><expression>if ([ID Number] in ([IDR Foundation Query].[id]))
then (1)
else (0)</expression></dataItem><dataItem name="School"><expression>if ([ID Number] in ([IDR School Query].[id]))
then (1)
else (0)</expression></dataItem><dataItem name="Total"><expression>[Person] + [Business] + [Organization] + [Church] + [Foundation] + [School]</expression></dataItem><dataItem name="Office Added By Code" aggregate="none" rollupAggregate="none"><expression>[General Information].[Name and Address].[Office Added By Code]</expression><XMLAttributes><XMLAttribute name="RS_dataType" value="3" output="no"/><XMLAttribute name="RS_dataUsage" value="attribute" output="no"/></XMLAttributes></dataItem></selection><detailFilters><detailFilter use="required" postAutoAggregation="false"><filterExpression>[Total] = 0 or [Total] &gt; 1</filterExpression></detailFilter></detailFilters></query><query name="States and Country Match Query"><source><model/></source><selection><dataItem name="ID Number" aggregate="none" rollupAggregate="none"><expression>[General Information].[Name and Address].[ID Number]</expression><XMLAttributes><XMLAttribute name="RS_dataType" value="1" output="no"/><XMLAttribute name="RS_dataUsage" value="identifier" output="no"/></XMLAttributes></dataItem><dataItem name="Full Name (Last, First)" aggregate="none" rollupAggregate="none"><expression>[General Information].[Name and Address].[Full Name (Last, First)]</expression><XMLAttributes><XMLAttribute name="RS_dataType" value="3" output="no"/><XMLAttribute name="RS_dataUsage" value="identifier" output="no"/></XMLAttributes></dataItem><dataItem name="State Code" aggregate="none" rollupAggregate="none"><expression>[General Information].[Name and Address].[State Code]</expression><XMLAttributes><XMLAttribute name="RS_dataType" value="3" output="no"/><XMLAttribute name="RS_dataUsage" value="attribute" output="no"/></XMLAttributes></dataItem><dataItem name="Country Code" aggregate="none" rollupAggregate="none"><expression>[General Information].[Name and Address].[Country Code]</expression><XMLAttributes><XMLAttribute name="RS_dataType" value="3" output="no"/><XMLAttribute name="RS_dataUsage" value="attribute" output="no"/></XMLAttributes></dataItem><dataItem name="Address Line 1" aggregate="none" rollupAggregate="none"><expression>[General Information].[Name and Address].[Address Line 1]</expression><XMLAttributes><XMLAttribute name="RS_dataType" value="3" output="no"/><XMLAttribute name="RS_dataUsage" value="attribute" output="no"/></XMLAttributes></dataItem><dataItem name="City" aggregate="none" rollupAggregate="none"><expression>[General Information].[Name and Address].[City]</expression><XMLAttributes><XMLAttribute name="RS_dataType" value="3" output="no"/><XMLAttribute name="RS_dataUsage" value="attribute" output="no"/></XMLAttributes></dataItem><dataItemListSummary refDataItem="ID Number" aggregateMethod="countDistinct" name="Count Distinct(ID Number)"/></selection><detailFilters><detailFilter use="required" postAutoAggregation="false"><filterExpression>( ( [Country Code] = 'CDN' )and ( [State Code] not in ('AB', 'BC', 'MB', 'NB', 'NF', 'NS', 'NT', 'ON', 'PE', 'SK', 'YT', 'PQ', 'NU', 'NL', 'QC') ) )
or
( ( [Country Code] = 'USA' ) and ( [State Code] not in ([USA States].[st])))
or
( ( [Country Code] not in ('USA', 'CDN' ) ) and ( [State Code] &lt;&gt; '--' ) )</filterExpression></detailFilter></detailFilters></query><query name="USA States">
			<source>
				<sqlQuery name="SQL7" dataSource="CX">
					<sqlText>select st from st_table where
web_ord &gt; 49
and web_ord &lt; 70</sqlText>
					<mdProjectedItems><mdProjectedItem name="st"/></mdProjectedItems></sqlQuery></source>
			<selection><dataItem name="st"><expression>[SQL7].[st]</expression></dataItem></selection>
		</query><query name="Hispanic Matches Race Query"><source><model/></source><selection><dataItem name="ID Number" aggregate="none" rollupAggregate="none"><expression>[General Information].[Profile].[ID Number]</expression><XMLAttributes><XMLAttribute name="RS_dataType" value="1" output="no"/><XMLAttribute name="RS_dataUsage" value="identifier" output="no"/></XMLAttributes></dataItem><dataItem name="Full Name" aggregate="none" rollupAggregate="none"><expression>[General Information].[Profile].[Full Name]</expression><XMLAttributes><XMLAttribute name="RS_dataType" value="3" output="no"/><XMLAttribute name="RS_dataUsage" value="identifier" output="no"/></XMLAttributes></dataItem><dataItem name="Ethnic Code (New)" aggregate="none" rollupAggregate="none"><expression>[General Information].[Profile].[Ethnic Code (New)]</expression><XMLAttributes><XMLAttribute name="RS_dataType" value="3" output="no"/><XMLAttribute name="RS_dataUsage" value="attribute" output="no"/></XMLAttributes></dataItem><dataItem name="Hispanic - Y/N" aggregate="none" rollupAggregate="none"><expression>[General Information].[Profile].[Hispanic - Y/N]</expression><XMLAttributes><XMLAttribute name="RS_dataType" value="3" output="no"/><XMLAttribute name="RS_dataUsage" value="attribute" output="no"/></XMLAttributes></dataItem><dataItemListSummary refDataItem="ID Number" aggregateMethod="countDistinct" name="Count Distinct(ID Number)"/></selection><detailFilters><detailFilter use="required" postAutoAggregation="false"><filterExpression>( [Ethnic Code (New)] not in ('HI', 'MU') and [Hispanic - Y/N] = 'Y' )
or
( [Ethnic Code (New)] = 'HI' and [Hispanic - Y/N] = 'N' )
or
( [Ethnic Code (New)] = 'MU' and [Hispanic - Y/N] = 'N' and [ID Number] in ([Hispanic - Multi Race Query].[Multi-Ethnic ID Number]) )</filterExpression></detailFilter></detailFilters></query><query name="Hispanic - Multi Race Query">
			<source>
				<model/>
			</source>
			<selection><dataItem name="Multi-Ethnic ID Number" aggregate="none" rollupAggregate="none"><expression>[General Information].[Mulit-Race Record].[Multi-Ethnic ID Number]</expression><XMLAttributes><XMLAttribute name="RS_dataType" value="1" output="no"/><XMLAttribute name="RS_dataUsage" value="identifier" output="no"/></XMLAttributes></dataItem><dataItem name="Multi Ethnic Code" aggregate="none" rollupAggregate="none"><expression>[General Information].[Mulit-Race Record].[Multi Ethnic Code]</expression><XMLAttributes><XMLAttribute name="RS_dataType" value="3" output="no"/><XMLAttribute name="RS_dataUsage" value="attribute" output="no"/></XMLAttributes></dataItem></selection>
			<detailFilters><detailFilter><filterExpression>[Multi Ethnic Code] = 'HI'</filterExpression></detailFilter></detailFilters></query><query name="ID Rec CTRY exists Query"><source><model/></source><selection><dataItem name="Country Code" aggregate="none" rollupAggregate="none"><expression>[General Information].[Name and Address].[Country Code]</expression><XMLAttributes><XMLAttribute name="RS_dataType" value="3" output="no"/><XMLAttribute name="RS_dataUsage" value="attribute" output="no"/></XMLAttributes></dataItem><dataItem name="ID Number" aggregate="none" rollupAggregate="none"><expression>[General Information].[Name and Address].[ID Number]</expression><XMLAttributes><XMLAttribute name="RS_dataType" value="1" output="no"/><XMLAttribute name="RS_dataUsage" value="identifier" output="no"/></XMLAttributes></dataItem><dataItem name="Full Name (Last, First)" aggregate="none" rollupAggregate="none"><expression>[General Information].[Name and Address].[Full Name (Last, First)]</expression><XMLAttributes><XMLAttribute name="RS_dataType" value="3" output="no"/><XMLAttribute name="RS_dataUsage" value="identifier" output="no"/></XMLAttributes></dataItem><dataItemListSummary refDataItem="ID Number" aggregateMethod="countDistinct" name="Count Distinct(ID Number)"/><dataItem name="Address Line 1" aggregate="none" rollupAggregate="none"><expression>[General Information].[Name and Address].[Address Line 1]</expression><XMLAttributes><XMLAttribute name="RS_dataType" value="3" output="no"/><XMLAttribute name="RS_dataUsage" value="attribute" output="no"/></XMLAttributes></dataItem><dataItem name="Address Line 2 - Calculated" aggregate="none" rollupAggregate="none"><expression>[General Information].[Name and Address].[Address Line 2 - Calculated]</expression><XMLAttributes><XMLAttribute name="RS_dataType" value="3" output="no"/><XMLAttribute name="RS_dataUsage" value="attribute" output="no"/></XMLAttributes></dataItem><dataItem name="Address Line 3 - Calculated" aggregate="none" rollupAggregate="none"><expression>[General Information].[Name and Address].[Address Line 3 - Calculated]</expression><XMLAttributes><XMLAttribute name="RS_dataType" value="3" output="no"/><XMLAttribute name="RS_dataUsage" value="attribute" output="no"/></XMLAttributes></dataItem><dataItem name="Address Line 4 - Calculated" aggregate="none" rollupAggregate="none"><expression>[General Information].[Name and Address].[Address Line 4 - Calculated]</expression><XMLAttributes><XMLAttribute name="RS_dataType" value="3" output="no"/><XMLAttribute name="RS_dataUsage" value="attribute" output="no"/></XMLAttributes></dataItem></selection><detailFilters><detailFilter><filterDefinition><filterInValues refDataItem="Country Code" dataType="string"><filterValues><filterValue>
								</filterValue></filterValues></filterInValues></filterDefinition></detailFilter></detailFilters></query><query name="State in Program Enrollment Matches Profile Query"><source><model/></source><selection><dataItem name="ID Number" aggregate="none" rollupAggregate="none"><expression>[General Information].[Profile].[ID Number]</expression><XMLAttributes><XMLAttribute name="RS_dataType" value="1" output="no"/><XMLAttribute name="RS_dataUsage" value="identifier" output="no"/></XMLAttributes></dataItem><dataItem name="Full Name" aggregate="none" rollupAggregate="none"><expression>[General Information].[Profile].[Full Name]</expression><XMLAttributes><XMLAttribute name="RS_dataType" value="3" output="no"/><XMLAttribute name="RS_dataUsage" value="identifier" output="no"/></XMLAttributes></dataItem><dataItem name="Resident State Code" aggregate="none" rollupAggregate="none"><expression>[General Information].[Profile].[Resident State Code]</expression><XMLAttributes><XMLAttribute name="RS_dataType" value="3" output="no"/><XMLAttribute name="RS_dataUsage" value="attribute" output="no"/></XMLAttributes></dataItem><dataItem name="Resident Country Code" aggregate="none" rollupAggregate="none"><expression>[General Information].[Profile].[Resident Country Code]</expression><XMLAttributes><XMLAttribute name="RS_dataType" value="3" output="no"/><XMLAttribute name="RS_dataUsage" value="attribute" output="no"/></XMLAttributes></dataItem><dataItem name="Program Enrollment State Code" aggregate="none" rollupAggregate="none"><expression>[Student Academic].[Program Enrollment].[Resident State Code]</expression><XMLAttributes><XMLAttribute name="RS_dataType" value="3" output="no"/><XMLAttribute name="RS_dataUsage" value="attribute" output="no"/></XMLAttributes></dataItem><dataItemListSummary refDataItem="ID Number" aggregateMethod="countDistinct" name="Count Distinct(ID Number)"/></selection><detailFilters><detailFilter use="required" postAutoAggregation="false"><filterExpression>[Resident State Code] &lt;&gt; [Program Enrollment State Code]</filterExpression></detailFilter><detailFilter use="required" postAutoAggregation="false"><filterExpression>[ID Number] = [Student Academic].[Program Enrollment].[Student ID Number]</filterExpression></detailFilter></detailFilters></query><query name="Title matches Profile Query"><source><model/></source><selection><dataItem name="Title Code" aggregate="none" rollupAggregate="none"><expression>[General Information].[Name and Address].[Title Code]</expression><XMLAttributes><XMLAttribute name="RS_dataType" value="3" output="no"/><XMLAttribute name="RS_dataUsage" value="attribute" output="no"/></XMLAttributes></dataItem><dataItem name="ID Number" aggregate="none" rollupAggregate="none"><expression>[General Information].[Name and Address].[ID Number]</expression><XMLAttributes><XMLAttribute name="RS_dataType" value="1" output="no"/><XMLAttribute name="RS_dataUsage" value="identifier" output="no"/></XMLAttributes></dataItem><dataItem name="Full Name (Last, First)" aggregate="none" rollupAggregate="none"><expression>[General Information].[Name and Address].[Full Name (Last, First)]</expression><XMLAttributes><XMLAttribute name="RS_dataType" value="3" output="no"/><XMLAttribute name="RS_dataUsage" value="identifier" output="no"/></XMLAttributes></dataItem><dataItem name="Profile Exists"><expression>if ( [ID Number] in ( [IDR Profile Query].[id] ) ) then ('yes') else ('no')</expression></dataItem><dataItemListSummary refDataItem="ID Number" aggregateMethod="countDistinct" name="Count Distinct(ID Number)"/></selection><detailFilters><detailFilter use="required" postAutoAggregation="false"><filterExpression>( ( [Title Code] = ' ' ) AND ( [Profile Exists] = 'yes' )  ) OR (  ( [Title Code] not in (NULL, '', ' ' ) )  AND ( [Profile Exists] = 'no' ) )</filterExpression></detailFilter></detailFilters></query><query name="Suffixname_table query">
			<source>
				<sqlQuery name="SQL8" dataSource="CX">
					<sqlText>select * from suffixname_table</sqlText>
					<mdProjectedItems><mdProjectedItem name="suffixname"/><mdProjectedItem name="txt"/><mdProjectedItem name="web_ord"/><mdProjectedItem name="active_date"/><mdProjectedItem name="inactive_date"/></mdProjectedItems></sqlQuery></source>
			<selection><dataItem name="suffixname"><expression>[SQL8].[suffixname]</expression></dataItem><dataItem name="txt"><expression>[SQL8].[txt]</expression></dataItem><dataItem name="web_ord"><expression>[SQL8].[web_ord]</expression></dataItem><dataItem name="active_date"><expression>[SQL8].[active_date]</expression></dataItem><dataItem name="inactive_date"><expression>[SQL8].[inactive_date]</expression></dataItem></selection>
		</query><query name="Query1"><source><model/></source><selection><dataItem name="ID Number" aggregate="none" rollupAggregate="none"><expression>[General Information].[Name and Address].[ID Number]</expression><XMLAttributes><XMLAttribute name="RS_dataType" value="1" output="no"/><XMLAttribute name="RS_dataUsage" value="identifier" output="no"/></XMLAttributes></dataItem><dataItem name="Full Name (Last, First)" aggregate="none" rollupAggregate="none"><expression>[General Information].[Name and Address].[Full Name (Last, First)]</expression><XMLAttributes><XMLAttribute name="RS_dataType" value="3" output="no"/><XMLAttribute name="RS_dataUsage" value="identifier" output="no"/></XMLAttributes></dataItem><dataItem name="Name Suffix" aggregate="none" rollupAggregate="none"><expression>[General Information].[Name and Address].[Name Suffix]</expression><XMLAttributes><XMLAttribute name="RS_dataType" value="3" output="no"/><XMLAttribute name="RS_dataUsage" value="attribute" output="no"/></XMLAttributes></dataItem></selection><detailFilters><detailFilter use="required" postAutoAggregation="false"><filterExpression>[Name Suffix] &lt;&gt; '' AND [Name Suffix] not in ( [Suffixname_table query].[suffixname] )</filterExpression></detailFilter></detailFilters></query></queries>
	<layouts>
		<layout>
			<reportPages>
				<page name="Race Check Page"><style><defaultStyles><defaultStyle refStyle="pg"/></defaultStyles></style>
					<pageBody><style><defaultStyles><defaultStyle refStyle="pb"/></defaultStyles></style>
						<contents>
							<table repeatOnPageBreak="false" allowPageBreaksWithinRow="false"><style><defaultStyles><defaultStyle refStyle="tb"/></defaultStyles><CSS value="border-collapse:collapse"/></style><tableRows><tableRow><tableCells><tableCell><contents><textItem><dataSource><staticValue>Profile Rec Race Code Blank</staticValue></dataSource><style><CSS value="font-weight:bold"/></style></textItem></contents></tableCell></tableCells></tableRow><tableRow><tableCells><tableCell><contents><list horizontalPagination="true" name="List1" refQuery="Race Query">
														<noDataHandler>
															<contents>
																<block>
																	<contents>
																		<textItem>
																			<dataSource>
																				<staticValue>No Data Available</staticValue>
																			</dataSource>
																			<style>
																				<CSS value="padding:10px 18px;"/>
																			</style>
																		</textItem>
																	</contents>
																</block>
															</contents>
														</noDataHandler>
														<style>
															<defaultStyles>
																<defaultStyle refStyle="ls"/>
															</defaultStyles>
															<CSS value="border-collapse:collapse"/>
														</style>
														<listColumns><listColumn><listColumnTitle><style><defaultStyles><defaultStyle refStyle="lt"/></defaultStyles></style><contents><textItem><dataSource><dataItemLabel refDataItem="ID Number"/></dataSource></textItem></contents></listColumnTitle><listColumnBody><style><defaultStyles><defaultStyle refStyle="lc"/></defaultStyles></style><contents><textItem><dataSource><dataItemValue refDataItem="ID Number"/></dataSource></textItem></contents></listColumnBody></listColumn><listColumn><listColumnTitle><style><defaultStyles><defaultStyle refStyle="lt"/></defaultStyles></style><contents><textItem><dataSource><dataItemLabel refDataItem="Full Name"/></dataSource></textItem></contents></listColumnTitle><listColumnBody><style><defaultStyles><defaultStyle refStyle="lc"/></defaultStyles></style><contents><textItem><dataSource><dataItemValue refDataItem="Full Name"/></dataSource></textItem></contents></listColumnBody></listColumn><listColumn><listColumnTitle><style><defaultStyles><defaultStyle refStyle="lt"/></defaultStyles></style><contents><textItem><dataSource><dataItemLabel refDataItem="Office Added By Code"/></dataSource></textItem></contents></listColumnTitle><listColumnBody><style><defaultStyles><defaultStyle refStyle="lc"/></defaultStyles></style><contents><textItem><dataSource><dataItemValue refDataItem="Office Added By Code"/></dataSource></textItem></contents></listColumnBody></listColumn><listColumn><listColumnTitle><style><defaultStyles><defaultStyle refStyle="lt"/></defaultStyles></style><contents><textItem><dataSource><dataItemLabel refDataItem="Race Code"/></dataSource></textItem></contents></listColumnTitle><listColumnBody><style><defaultStyles><defaultStyle refStyle="lc"/></defaultStyles></style><contents><textItem><dataSource><dataItemValue refDataItem="Race Code"/></dataSource></textItem></contents></listColumnBody></listColumn><listColumn><listColumnTitle><style><defaultStyles><defaultStyle refStyle="lt"/></defaultStyles></style><contents><textItem><dataSource><dataItemLabel refDataItem="Ethnic Code"/></dataSource></textItem></contents></listColumnTitle><listColumnBody><style><defaultStyles><defaultStyle refStyle="lc"/></defaultStyles></style><contents><textItem><dataSource><dataItemValue refDataItem="Ethnic Code"/></dataSource></textItem></contents></listColumnBody></listColumn></listColumns><listOverallGroup><listFooter><listRows><listRow><rowCells><rowCell><contents><textItem><dataSource><dataItemValue refDataItem="Count Distinct(ID Number)"/></dataSource></textItem></contents><style><defaultStyles><defaultStyle refStyle="is"/></defaultStyles></style></rowCell><rowCell colSpan="4"><contents><textItem><dataSource><staticValue>Overall</staticValue></dataSource></textItem><textItem><dataSource><staticValue> - </staticValue></dataSource></textItem><textItem><dataSource><staticValue>Count Distinct</staticValue></dataSource></textItem></contents><style><defaultStyles><defaultStyle refStyle="if"/></defaultStyles></style></rowCell></rowCells></listRow></listRows></listFooter></listOverallGroup></list></contents></tableCell></tableCells></tableRow></tableRows></table></contents>
					</pageBody>
					<pageHeader>
						<contents>
							<block><style><defaultStyles><defaultStyle refStyle="ta"/></defaultStyles></style>
								<contents>
									<textItem><style><defaultStyles><defaultStyle refStyle="tt"/></defaultStyles></style>
										<dataSource>
											<staticValue/>
										</dataSource>
									</textItem>
								</contents>
							</block>
						</contents>
						<style>
							<defaultStyles>
								<defaultStyle refStyle="ph"/>
							</defaultStyles>
							<CSS value="padding-bottom:10px"/>
						</style>
					</pageHeader>
					<pageFooter>
						<contents>
							<table>
								<tableRows>
									<tableRow>
										<tableCells>
											<tableCell>
												<contents>
													<date>
														<style>
															<dataFormat>
																<dateFormat/>
															</dataFormat>
														</style>
													</date>
												</contents>
												<style>
													<CSS value="vertical-align:top;text-align:left;width:25%"/>
												</style>
											</tableCell>
											<tableCell>
												<contents>
													<pageNumber/>
												</contents>
												<style>
													<CSS value="vertical-align:top;text-align:center;width:50%"/>
												</style>
											</tableCell>
											<tableCell>
												<contents>
													<time>
														<style>
															<dataFormat>
																<timeFormat/>
															</dataFormat>
														</style>
													</time>
												</contents>
												<style>
													<CSS value="vertical-align:top;text-align:right;width:25%"/>
												</style>
											</tableCell>
										</tableCells>
									</tableRow>
								</tableRows>
								<style>
									<defaultStyles>
										<defaultStyle refStyle="tb"/>
									</defaultStyles>
									<CSS value="border-collapse:collapse;width:100%"/>
								</style>
							</table>
						</contents>
						<style>
							<defaultStyles>
								<defaultStyle refStyle="pf"/>
							</defaultStyles>
							<CSS value="padding-top:10px"/>
						</style>
					</pageFooter>
				</page>
				<page name="Match Hispanic and Race">
					<pageBody>
						<contents><textItem><dataSource><staticValue>Hispanic field matches Race field</staticValue></dataSource></textItem><list horizontalPagination="true" name="List7" refQuery="Hispanic Matches Race Query">
								<noDataHandler>
									<contents>
										<block>
											<contents>
												<textItem>
													<dataSource>
														<staticValue>No Data Available</staticValue>
													</dataSource>
													<style>
														<CSS value="padding:10px 18px;"/>
													</style>
												</textItem>
											</contents>
										</block>
									</contents>
								</noDataHandler>
								<style>
									<CSS value="border-collapse:collapse"/>
									<defaultStyles>
										<defaultStyle refStyle="ls"/>
									</defaultStyles>
								</style>
								<listColumns><listColumn><listColumnTitle><style><defaultStyles><defaultStyle refStyle="lt"/></defaultStyles></style><contents><textItem><dataSource><dataItemLabel refDataItem="ID Number"/></dataSource></textItem></contents></listColumnTitle><listColumnBody><style><defaultStyles><defaultStyle refStyle="lc"/></defaultStyles></style><contents><textItem><dataSource><dataItemValue refDataItem="ID Number"/></dataSource></textItem></contents></listColumnBody></listColumn><listColumn><listColumnTitle><style><defaultStyles><defaultStyle refStyle="lt"/></defaultStyles></style><contents><textItem><dataSource><dataItemLabel refDataItem="Full Name"/></dataSource></textItem></contents></listColumnTitle><listColumnBody><style><defaultStyles><defaultStyle refStyle="lc"/></defaultStyles></style><contents><textItem><dataSource><dataItemValue refDataItem="Full Name"/></dataSource></textItem></contents></listColumnBody></listColumn><listColumn><listColumnTitle><style><defaultStyles><defaultStyle refStyle="lt"/></defaultStyles></style><contents><textItem><dataSource><staticValue>Race</staticValue></dataSource></textItem></contents></listColumnTitle><listColumnBody><style><defaultStyles><defaultStyle refStyle="lc"/></defaultStyles></style><contents><textItem><dataSource><dataItemValue refDataItem="Ethnic Code (New)"/></dataSource></textItem></contents></listColumnBody></listColumn><listColumn><listColumnTitle><style><defaultStyles><defaultStyle refStyle="lt"/></defaultStyles></style><contents><textItem><dataSource><dataItemLabel refDataItem="Hispanic - Y/N"/></dataSource></textItem></contents></listColumnTitle><listColumnBody><style><defaultStyles><defaultStyle refStyle="lc"/></defaultStyles></style><contents><textItem><dataSource><dataItemValue refDataItem="Hispanic - Y/N"/></dataSource></textItem></contents></listColumnBody></listColumn></listColumns><sortList><sortItem refDataItem="Ethnic Code (New)" sortOrder="ascending"/></sortList><listOverallGroup><listFooter><listRows><listRow><rowCells><rowCell><contents><textItem><dataSource><dataItemValue refDataItem="Count Distinct(ID Number)"/></dataSource></textItem></contents><style><defaultStyles><defaultStyle refStyle="is"/></defaultStyles></style></rowCell><rowCell colSpan="3"><contents><textItem><dataSource><staticValue>Overall</staticValue></dataSource></textItem><textItem><dataSource><staticValue> - </staticValue></dataSource></textItem><textItem><dataSource><staticValue>Count Distinct</staticValue></dataSource></textItem></contents><style><defaultStyles><defaultStyle refStyle="if"/></defaultStyles></style></rowCell></rowCells></listRow></listRows></listFooter></listOverallGroup></list></contents>
						<style>
							<defaultStyles>
								<defaultStyle refStyle="pb"/>
							</defaultStyles>
						</style>
					</pageBody>
					<style>
						<defaultStyles>
							<defaultStyle refStyle="pg"/>
						</defaultStyles>
					</style>
				</page><page name="Title-Gender Page">
					<pageBody>
						<contents><table><style><defaultStyles><defaultStyle refStyle="tb"/></defaultStyles><CSS value="border-collapse:collapse;width:100%"/></style><tableRows><tableRow><tableCells><tableCell><contents><textItem><dataSource><staticValue>Title Matches Gender</staticValue></dataSource><style><CSS value="font-weight:bold"/></style></textItem></contents></tableCell></tableCells></tableRow><tableRow><tableCells><tableCell><contents><list horizontalPagination="true" name="List2" refQuery="Title Query">
														<noDataHandler>
															<contents>
																<block>
																	<contents>
																		<textItem>
																			<dataSource>
																				<staticValue>No Data Available</staticValue>
																			</dataSource>
																			<style>
																				<CSS value="padding:10px 18px;"/>
																			</style>
																		</textItem>
																	</contents>
																</block>
															</contents>
														</noDataHandler>
														<style>
															<CSS value="border-collapse:collapse"/>
															<defaultStyles>
																<defaultStyle refStyle="ls"/>
															</defaultStyles>
														</style>
														<listColumns><listColumn><listColumnTitle><style><defaultStyles><defaultStyle refStyle="lt"/></defaultStyles></style><contents><textItem><dataSource><dataItemLabel refDataItem="Gender Code"/></dataSource></textItem></contents></listColumnTitle><listColumnBody><style><defaultStyles><defaultStyle refStyle="lc"/></defaultStyles></style><contents><textItem><dataSource><dataItemValue refDataItem="Gender Code"/></dataSource></textItem></contents><listColumnRowSpan refDataItem="Gender Code"/></listColumnBody></listColumn><listColumn><listColumnTitle><style><defaultStyles><defaultStyle refStyle="lt"/></defaultStyles></style><contents><textItem><dataSource><dataItemLabel refDataItem="Title Code"/></dataSource></textItem></contents></listColumnTitle><listColumnBody><style><defaultStyles><defaultStyle refStyle="lc"/></defaultStyles></style><contents><textItem><dataSource><dataItemValue refDataItem="Title Code"/></dataSource></textItem></contents><listColumnRowSpan refDataItem="Title Code"/></listColumnBody></listColumn><listColumn><listColumnTitle><style><defaultStyles><defaultStyle refStyle="lt"/></defaultStyles></style><contents><textItem><dataSource><dataItemLabel refDataItem="ID Number"/></dataSource></textItem></contents></listColumnTitle><listColumnBody><style><defaultStyles><defaultStyle refStyle="lc"/></defaultStyles></style><contents><textItem><dataSource><dataItemValue refDataItem="ID Number"/></dataSource></textItem></contents></listColumnBody></listColumn><listColumn><listColumnTitle><style><defaultStyles><defaultStyle refStyle="lt"/></defaultStyles></style><contents><textItem><dataSource><dataItemLabel refDataItem="Full Name"/></dataSource></textItem></contents></listColumnTitle><listColumnBody><style><defaultStyles><defaultStyle refStyle="lc"/></defaultStyles></style><contents><textItem><dataSource><dataItemValue refDataItem="Full Name"/></dataSource></textItem></contents></listColumnBody></listColumn><listColumn><listColumnTitle><style><defaultStyles><defaultStyle refStyle="lt"/></defaultStyles></style><contents><textItem><dataSource><dataItemLabel refDataItem="Office Added By Code"/></dataSource></textItem></contents></listColumnTitle><listColumnBody><style><defaultStyles><defaultStyle refStyle="lc"/></defaultStyles></style><contents><textItem><dataSource><dataItemValue refDataItem="Office Added By Code"/></dataSource></textItem></contents></listColumnBody></listColumn></listColumns><listGroups><listGroup refDataItem="Gender Code"/><listGroup refDataItem="Title Code"/></listGroups><listOverallGroup><listFooter><listRows><listRow><rowCells><rowCell colSpan="2"><contents><textItem><dataSource><staticValue>Overall</staticValue></dataSource></textItem><textItem><dataSource><staticValue> - </staticValue></dataSource></textItem><textItem><dataSource><staticValue>Count Distinct</staticValue></dataSource></textItem></contents><style><defaultStyles><defaultStyle refStyle="if"/></defaultStyles></style></rowCell><rowCell><contents><textItem><dataSource><dataItemValue refDataItem="Count Distinct(ID Number)"/></dataSource></textItem></contents><style><defaultStyles><defaultStyle refStyle="is"/></defaultStyles></style></rowCell><rowCell><contents/><style><defaultStyles><defaultStyle refStyle="if"/></defaultStyles></style></rowCell><rowCell><contents/><style><defaultStyles><defaultStyle refStyle="if"/></defaultStyles></style></rowCell></rowCells></listRow></listRows></listFooter></listOverallGroup></list></contents></tableCell></tableCells></tableRow></tableRows></table></contents>
						<style>
							<defaultStyles>
								<defaultStyle refStyle="pb"/>
							</defaultStyles>
						</style>
					</pageBody>
					<style>
						<defaultStyles>
							<defaultStyle refStyle="pg"/>
						</defaultStyles>
					</style>
				</page><page name="MRS Title are Married">
					<pageBody>
						<contents><table><style><defaultStyles><defaultStyle refStyle="tb"/></defaultStyles><CSS value="border-collapse:collapse;width:100%"/></style><tableRows><tableRow><tableCells><tableCell><contents><textItem><dataSource><staticValue>MRS are all married</staticValue></dataSource><style><CSS value="font-weight:bold"/></style></textItem></contents></tableCell></tableCells></tableRow><tableRow><tableCells><tableCell><contents><list horizontalPagination="true" name="List6" refQuery="Married Title Query">
														<noDataHandler>
															<contents>
																<block>
																	<contents>
																		<textItem>
																			<dataSource>
																				<staticValue>No Data Available</staticValue>
																			</dataSource>
																			<style>
																				<CSS value="padding:10px 18px;"/>
																			</style>
																		</textItem>
																	</contents>
																</block>
															</contents>
														</noDataHandler>
														<style>
															<CSS value="border-collapse:collapse"/>
															<defaultStyles>
																<defaultStyle refStyle="ls"/>
															</defaultStyles>
														</style>
														<listColumns><listColumn><listColumnTitle><style><defaultStyles><defaultStyle refStyle="lt"/></defaultStyles></style><contents><textItem><dataSource><dataItemLabel refDataItem="ID Number"/></dataSource></textItem></contents></listColumnTitle><listColumnBody><style><defaultStyles><defaultStyle refStyle="lc"/></defaultStyles></style><contents><textItem><dataSource><dataItemValue refDataItem="ID Number"/></dataSource></textItem></contents></listColumnBody></listColumn><listColumn><listColumnTitle><style><defaultStyles><defaultStyle refStyle="lt"/></defaultStyles></style><contents><textItem><dataSource><dataItemLabel refDataItem="Full Name"/></dataSource></textItem></contents></listColumnTitle><listColumnBody><style><defaultStyles><defaultStyle refStyle="lc"/></defaultStyles></style><contents><textItem><dataSource><dataItemValue refDataItem="Full Name"/></dataSource></textItem></contents></listColumnBody></listColumn><listColumn><listColumnTitle><style><defaultStyles><defaultStyle refStyle="lt"/></defaultStyles></style><contents><textItem><dataSource><dataItemLabel refDataItem="Office Added By Code"/></dataSource></textItem></contents></listColumnTitle><listColumnBody><style><defaultStyles><defaultStyle refStyle="lc"/></defaultStyles></style><contents><textItem><dataSource><dataItemValue refDataItem="Office Added By Code"/></dataSource></textItem></contents></listColumnBody></listColumn><listColumn><listColumnTitle><style><defaultStyles><defaultStyle refStyle="lt"/></defaultStyles></style><contents><textItem><dataSource><dataItemLabel refDataItem="Marital Status Code"/></dataSource></textItem></contents></listColumnTitle><listColumnBody><style><defaultStyles><defaultStyle refStyle="lc"/></defaultStyles></style><contents><textItem><dataSource><dataItemValue refDataItem="Marital Status Code"/></dataSource></textItem></contents></listColumnBody></listColumn><listColumn><listColumnTitle><style><defaultStyles><defaultStyle refStyle="lt"/></defaultStyles></style><contents><textItem><dataSource><dataItemLabel refDataItem="Title Code"/></dataSource></textItem></contents></listColumnTitle><listColumnBody><style><defaultStyles><defaultStyle refStyle="lc"/></defaultStyles></style><contents><textItem><dataSource><dataItemValue refDataItem="Title Code"/></dataSource></textItem></contents></listColumnBody></listColumn><listColumn><listColumnTitle><style><defaultStyles><defaultStyle refStyle="lt"/></defaultStyles></style><contents><textItem><dataSource><dataItemLabel refDataItem="Relationship Code"/></dataSource></textItem></contents></listColumnTitle><listColumnBody><style><defaultStyles><defaultStyle refStyle="lc"/></defaultStyles></style><contents><textItem><dataSource><dataItemValue refDataItem="Relationship Code"/></dataSource></textItem></contents></listColumnBody></listColumn><listColumn><listColumnTitle><style><defaultStyles><defaultStyle refStyle="lt"/></defaultStyles></style><contents><textItem><dataSource><dataItemLabel refDataItem="Relation ID Number"/></dataSource></textItem></contents></listColumnTitle><listColumnBody><style><defaultStyles><defaultStyle refStyle="lc"/></defaultStyles></style><contents><textItem><dataSource><dataItemValue refDataItem="Relation ID Number"/></dataSource></textItem></contents></listColumnBody></listColumn><listColumn><listColumnTitle><style><defaultStyles><defaultStyle refStyle="lt"/></defaultStyles></style><contents><textItem><dataSource><dataItemLabel refDataItem="Primary ID Number"/></dataSource></textItem></contents></listColumnTitle><listColumnBody><style><defaultStyles><defaultStyle refStyle="lc"/></defaultStyles></style><contents><textItem><dataSource><dataItemValue refDataItem="Primary ID Number"/></dataSource></textItem></contents></listColumnBody></listColumn><listColumn><listColumnTitle><style><defaultStyles><defaultStyle refStyle="lt"/></defaultStyles></style><contents><textItem><dataSource><dataItemLabel refDataItem="Primary Name"/></dataSource></textItem></contents></listColumnTitle><listColumnBody><style><defaultStyles><defaultStyle refStyle="lc"/></defaultStyles></style><contents><textItem><dataSource><dataItemValue refDataItem="Primary Name"/></dataSource></textItem></contents></listColumnBody></listColumn></listColumns><sortList><sortItem refDataItem="Marital Status Code" sortOrder="ascending"/></sortList><listOverallGroup><listFooter><listRows><listRow><rowCells><rowCell><contents><textItem><dataSource><dataItemValue refDataItem="Count Distinct(ID Number)"/></dataSource></textItem></contents><style><defaultStyles><defaultStyle refStyle="is"/></defaultStyles></style></rowCell><rowCell colSpan="8"><contents><textItem><dataSource><staticValue>Overall</staticValue></dataSource></textItem><textItem><dataSource><staticValue> - </staticValue></dataSource></textItem><textItem><dataSource><staticValue>Count Distinct</staticValue></dataSource></textItem></contents><style><defaultStyles><defaultStyle refStyle="if"/></defaultStyles></style></rowCell></rowCells></listRow></listRows></listFooter></listOverallGroup></list></contents></tableCell></tableCells></tableRow></tableRows></table></contents>
						<style>
							<defaultStyles>
								<defaultStyle refStyle="pb"/>
							</defaultStyles>
						</style>
					</pageBody>
					<style>
						<defaultStyles>
							<defaultStyle refStyle="pg"/>
						</defaultStyles>
					</style>
				</page><page name="Cell Phones not in ID_Rec">
					<pageBody>
						<contents><table><style><defaultStyles><defaultStyle refStyle="tb"/></defaultStyles><CSS value="border-collapse:collapse;width:100%"/></style><tableRows><tableRow><tableCells><tableCell><contents><textItem><dataSource><staticValue>Cell Phones do not match ID Rec Phone Numbers</staticValue></dataSource><style><CSS value="font-weight:bold"/></style></textItem></contents></tableCell></tableCells></tableRow><tableRow><tableCells><tableCell><contents><list horizontalPagination="true" name="List4" refQuery="Cell Phone Query">
														<noDataHandler>
															<contents>
																<block>
																	<contents>
																		<textItem>
																			<dataSource>
																				<staticValue>No Data Available</staticValue>
																			</dataSource>
																			<style>
																				<CSS value="padding:10px 18px;"/>
																			</style>
																		</textItem>
																	</contents>
																</block>
															</contents>
														</noDataHandler>
														<style>
															<CSS value="border-collapse:collapse"/>
															<defaultStyles>
																<defaultStyle refStyle="ls"/>
															</defaultStyles>
														</style>
														<listColumns><listColumn><listColumnTitle><style><defaultStyles><defaultStyle refStyle="lt"/></defaultStyles></style><contents><textItem><dataSource><dataItemLabel refDataItem="ID Number"/></dataSource></textItem></contents></listColumnTitle><listColumnBody><style><defaultStyles><defaultStyle refStyle="lc"/></defaultStyles></style><contents><textItem><dataSource><dataItemValue refDataItem="ID Number"/></dataSource></textItem></contents></listColumnBody></listColumn><listColumn><listColumnTitle><style><defaultStyles><defaultStyle refStyle="lt"/></defaultStyles></style><contents><textItem><dataSource><dataItemLabel refDataItem="Full Name (Last, First)"/></dataSource></textItem></contents></listColumnTitle><listColumnBody><style><defaultStyles><defaultStyle refStyle="lc"/></defaultStyles></style><contents><textItem><dataSource><dataItemValue refDataItem="Full Name (Last, First)"/></dataSource></textItem></contents></listColumnBody></listColumn><listColumn><listColumnTitle><style><defaultStyles><defaultStyle refStyle="lt"/></defaultStyles></style><contents><textItem><dataSource><dataItemLabel refDataItem="Phone Number"/></dataSource></textItem></contents></listColumnTitle><listColumnBody><style><defaultStyles><defaultStyle refStyle="lc"/></defaultStyles></style><contents><textItem><dataSource><dataItemValue refDataItem="Phone Number"/></dataSource></textItem></contents></listColumnBody></listColumn><listColumn><listColumnTitle><style><defaultStyles><defaultStyle refStyle="lt"/></defaultStyles></style><contents><textItem><dataSource><dataItemLabel refDataItem="AA Code"/></dataSource></textItem></contents></listColumnTitle><listColumnBody><style><defaultStyles><defaultStyle refStyle="lc"/></defaultStyles></style><contents><textItem><dataSource><dataItemValue refDataItem="AA Code"/></dataSource></textItem></contents></listColumnBody></listColumn><listColumn><listColumnTitle><style><defaultStyles><defaultStyle refStyle="lt"/></defaultStyles></style><contents><textItem><dataSource><dataItemLabel refDataItem="AA Phone Number"/></dataSource></textItem></contents></listColumnTitle><listColumnBody><style><defaultStyles><defaultStyle refStyle="lc"/></defaultStyles></style><contents><textItem><dataSource><dataItemValue refDataItem="AA Phone Number"/></dataSource></textItem></contents></listColumnBody></listColumn><listColumn><listColumnTitle><style><defaultStyles><defaultStyle refStyle="lt"/></defaultStyles></style><contents><textItem><dataSource><dataItemLabel refDataItem="Office Added By Code"/></dataSource></textItem></contents></listColumnTitle><listColumnBody><style><defaultStyles><defaultStyle refStyle="lc"/></defaultStyles></style><contents><textItem><dataSource><dataItemValue refDataItem="Office Added By Code"/></dataSource></textItem></contents></listColumnBody></listColumn></listColumns><listOverallGroup><listFooter><listRows><listRow><rowCells><rowCell><contents><textItem><dataSource><dataItemValue refDataItem="Count Distinct(ID Number)"/></dataSource></textItem></contents><style><defaultStyles><defaultStyle refStyle="is"/></defaultStyles></style></rowCell><rowCell colSpan="5"><contents><textItem><dataSource><staticValue>Overall</staticValue></dataSource></textItem><textItem><dataSource><staticValue> - </staticValue></dataSource></textItem><textItem><dataSource><staticValue>Count Distinct</staticValue></dataSource></textItem></contents><style><defaultStyles><defaultStyle refStyle="if"/></defaultStyles></style></rowCell></rowCells></listRow></listRows></listFooter></listOverallGroup></list></contents></tableCell></tableCells></tableRow></tableRows></table></contents>
						<style>
							<defaultStyles>
								<defaultStyle refStyle="pb"/>
							</defaultStyles>
						</style>
					</pageBody>
					<style>
						<defaultStyles>
							<defaultStyle refStyle="pg"/>
						</defaultStyles>
					</style>
				</page><page name="Identifying Records">
					<pageBody>
						<contents><table><style><defaultStyles><defaultStyle refStyle="tb"/></defaultStyles><CSS value="border-collapse:collapse;width:100%"/></style><tableRows><tableRow><tableCells><tableCell><contents><textItem><dataSource><staticValue>Identifying Records</staticValue></dataSource><style><CSS value="font-weight:bold"/></style></textItem></contents></tableCell></tableCells></tableRow><tableRow><tableCells><tableCell><contents><list horizontalPagination="true" name="List5" refQuery="Identifying Records Query">
														<noDataHandler>
															<contents>
																<block>
																	<contents>
																		<textItem>
																			<dataSource>
																				<staticValue>No Data Available</staticValue>
																			</dataSource>
																			<style>
																				<CSS value="padding:10px 18px;"/>
																			</style>
																		</textItem>
																	</contents>
																</block>
															</contents>
														</noDataHandler>
														<style>
															<CSS value="border-collapse:collapse"/>
															<defaultStyles>
																<defaultStyle refStyle="ls"/>
															</defaultStyles>
														</style>
														<listColumns><listColumn><listColumnTitle><style><defaultStyles><defaultStyle refStyle="lt"/></defaultStyles></style><contents><textItem><dataSource><dataItemLabel refDataItem="ID Number"/></dataSource></textItem></contents></listColumnTitle><listColumnBody><style><defaultStyles><defaultStyle refStyle="lc"/></defaultStyles></style><contents><textItem><dataSource><dataItemValue refDataItem="ID Number"/></dataSource></textItem></contents></listColumnBody></listColumn><listColumn><listColumnTitle><style><defaultStyles><defaultStyle refStyle="lt"/></defaultStyles></style><contents><textItem><dataSource><dataItemLabel refDataItem="Full Name (Last, First)"/></dataSource></textItem></contents></listColumnTitle><listColumnBody><style><defaultStyles><defaultStyle refStyle="lc"/></defaultStyles></style><contents><textItem><dataSource><dataItemValue refDataItem="Full Name (Last, First)"/></dataSource></textItem></contents></listColumnBody></listColumn><listColumn><listColumnTitle><style><defaultStyles><defaultStyle refStyle="lt"/></defaultStyles></style><contents><textItem><dataSource><dataItemLabel refDataItem="Office Added By Code"/></dataSource></textItem></contents></listColumnTitle><listColumnBody><style><defaultStyles><defaultStyle refStyle="lc"/></defaultStyles></style><contents><textItem><dataSource><dataItemValue refDataItem="Office Added By Code"/></dataSource></textItem></contents></listColumnBody></listColumn><listColumn><listColumnTitle><style><defaultStyles><defaultStyle refStyle="lt"/></defaultStyles></style><contents><textItem><dataSource><dataItemLabel refDataItem="Person"/></dataSource></textItem></contents></listColumnTitle><listColumnBody><style><defaultStyles><defaultStyle refStyle="lm"/></defaultStyles></style><contents><textItem><dataSource><dataItemValue refDataItem="Person"/></dataSource></textItem></contents></listColumnBody></listColumn><listColumn><listColumnTitle><style><defaultStyles><defaultStyle refStyle="lt"/></defaultStyles></style><contents><textItem><dataSource><dataItemLabel refDataItem="School"/></dataSource></textItem></contents></listColumnTitle><listColumnBody><style><defaultStyles><defaultStyle refStyle="lm"/></defaultStyles></style><contents><textItem><dataSource><dataItemValue refDataItem="School"/></dataSource></textItem></contents></listColumnBody></listColumn><listColumn><listColumnTitle><style><defaultStyles><defaultStyle refStyle="lt"/></defaultStyles></style><contents><textItem><dataSource><dataItemLabel refDataItem="Business"/></dataSource></textItem></contents></listColumnTitle><listColumnBody><style><defaultStyles><defaultStyle refStyle="lm"/></defaultStyles></style><contents><textItem><dataSource><dataItemValue refDataItem="Business"/></dataSource></textItem></contents></listColumnBody></listColumn><listColumn><listColumnTitle><style><defaultStyles><defaultStyle refStyle="lt"/></defaultStyles></style><contents><textItem><dataSource><dataItemLabel refDataItem="Church"/></dataSource></textItem></contents></listColumnTitle><listColumnBody><style><defaultStyles><defaultStyle refStyle="lm"/></defaultStyles></style><contents><textItem><dataSource><dataItemValue refDataItem="Church"/></dataSource></textItem></contents></listColumnBody></listColumn><listColumn><listColumnTitle><style><defaultStyles><defaultStyle refStyle="lt"/></defaultStyles></style><contents><textItem><dataSource><dataItemLabel refDataItem="Foundation"/></dataSource></textItem></contents></listColumnTitle><listColumnBody><style><defaultStyles><defaultStyle refStyle="lm"/></defaultStyles></style><contents><textItem><dataSource><dataItemValue refDataItem="Foundation"/></dataSource></textItem></contents></listColumnBody></listColumn><listColumn><listColumnTitle><style><defaultStyles><defaultStyle refStyle="lt"/></defaultStyles></style><contents><textItem><dataSource><dataItemLabel refDataItem="Organization"/></dataSource></textItem></contents></listColumnTitle><listColumnBody><style><defaultStyles><defaultStyle refStyle="lm"/></defaultStyles></style><contents><textItem><dataSource><dataItemValue refDataItem="Organization"/></dataSource></textItem></contents></listColumnBody></listColumn><listColumn><listColumnTitle><style><defaultStyles><defaultStyle refStyle="lt"/></defaultStyles></style><contents><textItem><dataSource><dataItemLabel refDataItem="Total"/></dataSource></textItem></contents></listColumnTitle><listColumnBody><style><defaultStyles><defaultStyle refStyle="lm"/></defaultStyles></style><contents><textItem><dataSource><dataItemValue refDataItem="Total"/></dataSource></textItem></contents></listColumnBody></listColumn></listColumns></list></contents></tableCell></tableCells></tableRow></tableRows></table></contents>
						<style>
							<defaultStyles>
								<defaultStyle refStyle="pb"/>
							</defaultStyles>
						</style>
					</pageBody>
					<style>
						<defaultStyles>
							<defaultStyle refStyle="pg"/>
						</defaultStyles>
					</style>
				</page><page name="State and Country Match Check">
					<pageBody>
						<contents><textItem><dataSource><staticValue>Country Matches State?</staticValue></dataSource><style><CSS value="font-weight:bold"/></style></textItem><list horizontalPagination="true" name="List3" refQuery="States and Country Match Query">
								<noDataHandler>
									<contents>
										<block>
											<contents>
												<textItem>
													<dataSource>
														<staticValue>No Data Available</staticValue>
													</dataSource>
													<style>
														<CSS value="padding:10px 18px;"/>
													</style>
												</textItem>
											</contents>
										</block>
									</contents>
								</noDataHandler>
								<style>
									<CSS value="border-collapse:collapse"/>
									<defaultStyles>
										<defaultStyle refStyle="ls"/>
									</defaultStyles>
								</style>
								<listColumns><listColumn><listColumnTitle><style><defaultStyles><defaultStyle refStyle="lt"/></defaultStyles></style><contents><textItem><dataSource><dataItemLabel refDataItem="ID Number"/></dataSource></textItem></contents></listColumnTitle><listColumnBody><style><defaultStyles><defaultStyle refStyle="lc"/></defaultStyles></style><contents><textItem><dataSource><dataItemValue refDataItem="ID Number"/></dataSource></textItem></contents></listColumnBody></listColumn><listColumn><listColumnTitle><style><defaultStyles><defaultStyle refStyle="lt"/></defaultStyles></style><contents><textItem><dataSource><dataItemLabel refDataItem="Full Name (Last, First)"/></dataSource></textItem></contents></listColumnTitle><listColumnBody><style><defaultStyles><defaultStyle refStyle="lc"/></defaultStyles></style><contents><textItem><dataSource><dataItemValue refDataItem="Full Name (Last, First)"/></dataSource></textItem></contents></listColumnBody></listColumn><listColumn><listColumnTitle><style><defaultStyles><defaultStyle refStyle="lt"/></defaultStyles></style><contents><textItem><dataSource><dataItemLabel refDataItem="Address Line 1"/></dataSource></textItem></contents></listColumnTitle><listColumnBody><style><defaultStyles><defaultStyle refStyle="lc"/></defaultStyles></style><contents><textItem><dataSource><dataItemValue refDataItem="Address Line 1"/></dataSource></textItem></contents></listColumnBody></listColumn><listColumn><listColumnTitle><style><defaultStyles><defaultStyle refStyle="lt"/></defaultStyles></style><contents><textItem><dataSource><dataItemLabel refDataItem="City"/></dataSource></textItem></contents></listColumnTitle><listColumnBody><style><defaultStyles><defaultStyle refStyle="lc"/></defaultStyles></style><contents><textItem><dataSource><dataItemValue refDataItem="City"/></dataSource></textItem></contents></listColumnBody></listColumn><listColumn><listColumnTitle><style><defaultStyles><defaultStyle refStyle="lt"/></defaultStyles></style><contents><textItem><dataSource><dataItemLabel refDataItem="State Code"/></dataSource></textItem></contents></listColumnTitle><listColumnBody><style><defaultStyles><defaultStyle refStyle="lc"/></defaultStyles></style><contents><textItem><dataSource><dataItemValue refDataItem="State Code"/></dataSource></textItem></contents></listColumnBody></listColumn><listColumn><listColumnTitle><style><defaultStyles><defaultStyle refStyle="lt"/></defaultStyles></style><contents><textItem><dataSource><dataItemLabel refDataItem="Country Code"/></dataSource></textItem></contents></listColumnTitle><listColumnBody><style><defaultStyles><defaultStyle refStyle="lc"/></defaultStyles></style><contents><textItem><dataSource><dataItemValue refDataItem="Country Code"/></dataSource></textItem></contents></listColumnBody></listColumn></listColumns><sortList><sortItem refDataItem="Country Code" sortOrder="ascending"/></sortList><listOverallGroup><listFooter><listRows><listRow><rowCells><rowCell><contents><textItem><dataSource><dataItemValue refDataItem="Count Distinct(ID Number)"/></dataSource></textItem></contents><style><defaultStyles><defaultStyle refStyle="is"/></defaultStyles></style></rowCell><rowCell colSpan="5"><contents><textItem><dataSource><staticValue>Overall</staticValue></dataSource></textItem><textItem><dataSource><staticValue> - </staticValue></dataSource></textItem><textItem><dataSource><staticValue>Count Distinct</staticValue></dataSource></textItem></contents><style><defaultStyles><defaultStyle refStyle="if"/></defaultStyles></style></rowCell></rowCells></listRow></listRows></listFooter></listOverallGroup></list></contents>
						<style>
							<defaultStyles>
								<defaultStyle refStyle="pb"/>
							</defaultStyles>
						</style>
					</pageBody>
					<style>
						<defaultStyles>
							<defaultStyle refStyle="pg"/>
						</defaultStyles>
					</style>
				</page><page name="id_rec.ctry Exists">
					<pageBody>
						<contents><textItem><dataSource><staticValue>id_rec.ctry is not NULL</staticValue></dataSource><style><CSS value="font-weight:bold"/></style></textItem><list horizontalPagination="true" name="List8" refQuery="ID Rec CTRY exists Query">
								<noDataHandler>
									<contents>
										<block>
											<contents>
												<textItem>
													<dataSource>
														<staticValue>No Data Available</staticValue>
													</dataSource>
													<style>
														<CSS value="padding:10px 18px;"/>
													</style>
												</textItem>
											</contents>
										</block>
									</contents>
								</noDataHandler>
								<style>
									<CSS value="border-collapse:collapse"/>
									<defaultStyles>
										<defaultStyle refStyle="ls"/>
									</defaultStyles>
								</style>
								<listColumns><listColumn><listColumnTitle><style><defaultStyles><defaultStyle refStyle="lt"/></defaultStyles></style><contents><textItem><dataSource><dataItemLabel refDataItem="ID Number"/></dataSource></textItem></contents></listColumnTitle><listColumnBody><style><defaultStyles><defaultStyle refStyle="lc"/></defaultStyles></style><contents><textItem><dataSource><dataItemValue refDataItem="ID Number"/></dataSource></textItem></contents></listColumnBody></listColumn><listColumn><listColumnTitle><style><defaultStyles><defaultStyle refStyle="lt"/></defaultStyles></style><contents><textItem><dataSource><dataItemLabel refDataItem="Full Name (Last, First)"/></dataSource></textItem></contents></listColumnTitle><listColumnBody><style><defaultStyles><defaultStyle refStyle="lc"/></defaultStyles></style><contents><textItem><dataSource><dataItemValue refDataItem="Full Name (Last, First)"/></dataSource></textItem></contents></listColumnBody></listColumn><listColumn><listColumnTitle><style><defaultStyles><defaultStyle refStyle="lt"/></defaultStyles></style><contents><textItem><dataSource><dataItemLabel refDataItem="Address Line 1"/></dataSource></textItem></contents></listColumnTitle><listColumnBody><style><defaultStyles><defaultStyle refStyle="lc"/></defaultStyles></style><contents><textItem><dataSource><dataItemValue refDataItem="Address Line 1"/></dataSource></textItem></contents></listColumnBody></listColumn><listColumn><listColumnTitle><style><defaultStyles><defaultStyle refStyle="lt"/></defaultStyles></style><contents><textItem><dataSource><dataItemLabel refDataItem="Address Line 2 - Calculated"/></dataSource></textItem></contents></listColumnTitle><listColumnBody><style><defaultStyles><defaultStyle refStyle="lc"/></defaultStyles></style><contents><textItem><dataSource><dataItemValue refDataItem="Address Line 2 - Calculated"/></dataSource></textItem></contents></listColumnBody></listColumn><listColumn><listColumnTitle><style><defaultStyles><defaultStyle refStyle="lt"/></defaultStyles></style><contents><textItem><dataSource><dataItemLabel refDataItem="Address Line 3 - Calculated"/></dataSource></textItem></contents></listColumnTitle><listColumnBody><style><defaultStyles><defaultStyle refStyle="lc"/></defaultStyles></style><contents><textItem><dataSource><dataItemValue refDataItem="Address Line 3 - Calculated"/></dataSource></textItem></contents></listColumnBody></listColumn><listColumn><listColumnTitle><style><defaultStyles><defaultStyle refStyle="lt"/></defaultStyles></style><contents><textItem><dataSource><dataItemLabel refDataItem="Address Line 4 - Calculated"/></dataSource></textItem></contents></listColumnTitle><listColumnBody><style><defaultStyles><defaultStyle refStyle="lc"/></defaultStyles></style><contents><textItem><dataSource><dataItemValue refDataItem="Address Line 4 - Calculated"/></dataSource></textItem></contents></listColumnBody></listColumn><listColumn><listColumnTitle><style><defaultStyles><defaultStyle refStyle="lt"/></defaultStyles></style><contents><textItem><dataSource><dataItemLabel refDataItem="Country Code"/></dataSource></textItem></contents></listColumnTitle><listColumnBody><style><defaultStyles><defaultStyle refStyle="lc"/></defaultStyles></style><contents><textItem><dataSource><dataItemValue refDataItem="Country Code"/></dataSource></textItem></contents></listColumnBody></listColumn></listColumns><listOverallGroup><listFooter><listRows><listRow><rowCells><rowCell><contents><textItem><dataSource><dataItemValue refDataItem="Count Distinct(ID Number)"/></dataSource></textItem></contents><style><defaultStyles><defaultStyle refStyle="is"/></defaultStyles></style></rowCell><rowCell colSpan="6"><contents><textItem><dataSource><staticValue>Overall</staticValue></dataSource></textItem><textItem><dataSource><staticValue> - </staticValue></dataSource></textItem><textItem><dataSource><staticValue>Count Distinct</staticValue></dataSource></textItem></contents><style><defaultStyles><defaultStyle refStyle="if"/></defaultStyles></style></rowCell></rowCells></listRow></listRows></listFooter></listOverallGroup></list></contents>
						<style>
							<defaultStyles>
								<defaultStyle refStyle="pb"/>
							</defaultStyles>
						</style>
					</pageBody>
					<style>
						<defaultStyles>
							<defaultStyle refStyle="pg"/>
						</defaultStyles>
					</style>
				</page><page name="Program Enrollment State Matches Profile">
					<pageBody>
						<contents><textItem><dataSource><staticValue>Program Enrollment State matches Profile State</staticValue></dataSource></textItem><list horizontalPagination="true" name="List9" refQuery="State in Program Enrollment Matches Profile Query">
								<noDataHandler>
									<contents>
										<block>
											<contents>
												<textItem>
													<dataSource>
														<staticValue>No Data Available</staticValue>
													</dataSource>
													<style>
														<CSS value="padding:10px 18px;"/>
													</style>
												</textItem>
											</contents>
										</block>
									</contents>
								</noDataHandler>
								<style>
									<CSS value="border-collapse:collapse"/>
									<defaultStyles>
										<defaultStyle refStyle="ls"/>
									</defaultStyles>
								</style>
								<listColumns><listColumn><listColumnTitle><style><defaultStyles><defaultStyle refStyle="lt"/></defaultStyles></style><contents><textItem><dataSource><dataItemLabel refDataItem="ID Number"/></dataSource></textItem></contents></listColumnTitle><listColumnBody><style><defaultStyles><defaultStyle refStyle="lc"/></defaultStyles></style><contents><textItem><dataSource><dataItemValue refDataItem="ID Number"/></dataSource></textItem></contents></listColumnBody></listColumn><listColumn><listColumnTitle><style><defaultStyles><defaultStyle refStyle="lt"/></defaultStyles></style><contents><textItem><dataSource><dataItemLabel refDataItem="Full Name"/></dataSource></textItem></contents></listColumnTitle><listColumnBody><style><defaultStyles><defaultStyle refStyle="lc"/></defaultStyles></style><contents><textItem><dataSource><dataItemValue refDataItem="Full Name"/></dataSource></textItem></contents></listColumnBody></listColumn><listColumn><listColumnTitle><style><defaultStyles><defaultStyle refStyle="lt"/></defaultStyles></style><contents><textItem><dataSource><staticValue>Profile Res. State</staticValue></dataSource></textItem></contents></listColumnTitle><listColumnBody><style><defaultStyles><defaultStyle refStyle="lc"/></defaultStyles></style><contents><textItem><dataSource><dataItemValue refDataItem="Resident State Code"/></dataSource></textItem></contents></listColumnBody></listColumn><listColumn><listColumnTitle><style><defaultStyles><defaultStyle refStyle="lt"/></defaultStyles></style><contents><textItem><dataSource><staticValue>Profile Res CTRY</staticValue></dataSource></textItem></contents></listColumnTitle><listColumnBody><style><defaultStyles><defaultStyle refStyle="lc"/></defaultStyles></style><contents><textItem><dataSource><dataItemValue refDataItem="Resident Country Code"/></dataSource></textItem></contents></listColumnBody></listColumn><listColumn><listColumnTitle><style><defaultStyles><defaultStyle refStyle="lt"/></defaultStyles></style><contents><textItem><dataSource><staticValue>Prog_enr Res State</staticValue></dataSource></textItem></contents></listColumnTitle><listColumnBody><style><defaultStyles><defaultStyle refStyle="lc"/></defaultStyles></style><contents><textItem><dataSource><dataItemValue refDataItem="Program Enrollment State Code"/></dataSource></textItem></contents></listColumnBody></listColumn></listColumns><listOverallGroup><listFooter><listRows><listRow><rowCells><rowCell><contents><textItem><dataSource><dataItemValue refDataItem="Count Distinct(ID Number)"/></dataSource></textItem></contents><style><defaultStyles><defaultStyle refStyle="is"/></defaultStyles></style></rowCell><rowCell colSpan="4"><contents><textItem><dataSource><staticValue>Overall</staticValue></dataSource></textItem><textItem><dataSource><staticValue> - </staticValue></dataSource></textItem><textItem><dataSource><staticValue>Count Distinct</staticValue></dataSource></textItem></contents><style><defaultStyles><defaultStyle refStyle="if"/></defaultStyles></style></rowCell></rowCells></listRow></listRows></listFooter></listOverallGroup></list></contents>
						<style>
							<defaultStyles>
								<defaultStyle refStyle="pb"/>
							</defaultStyles>
						</style>
					</pageBody>
					<style>
						<defaultStyles>
							<defaultStyle refStyle="pg"/>
						</defaultStyles>
					</style>
				</page><page name="Titles have Profile">
					<pageBody>
						<contents><list horizontalPagination="true" name="List10" refQuery="Title matches Profile Query">
								<noDataHandler>
									<contents>
										<block>
											<contents>
												<textItem>
													<dataSource>
														<staticValue>No Data Available</staticValue>
													</dataSource>
													<style>
														<CSS value="padding:10px 18px;"/>
													</style>
												</textItem>
											</contents>
										</block>
									</contents>
								</noDataHandler>
								<style>
									<CSS value="border-collapse:collapse"/>
									<defaultStyles>
										<defaultStyle refStyle="ls"/>
									</defaultStyles>
								</style>
								<listColumns><listColumn><listColumnTitle><style><defaultStyles><defaultStyle refStyle="lt"/></defaultStyles></style><contents><textItem><dataSource><dataItemLabel refDataItem="Title Code"/></dataSource></textItem></contents></listColumnTitle><listColumnBody><style><defaultStyles><defaultStyle refStyle="lc"/></defaultStyles></style><contents><textItem><dataSource><dataItemValue refDataItem="Title Code"/></dataSource></textItem></contents><listColumnRowSpan refDataItem="Title Code"/></listColumnBody></listColumn><listColumn><listColumnTitle><style><defaultStyles><defaultStyle refStyle="lt"/></defaultStyles></style><contents><textItem><dataSource><dataItemLabel refDataItem="Profile Exists"/></dataSource></textItem></contents></listColumnTitle><listColumnBody><style><defaultStyles><defaultStyle refStyle="lm"/></defaultStyles></style><contents><textItem><dataSource><dataItemValue refDataItem="Profile Exists"/></dataSource></textItem></contents><listColumnRowSpan refDataItem="Profile Exists"/></listColumnBody></listColumn><listColumn><listColumnTitle><style><defaultStyles><defaultStyle refStyle="lt"/></defaultStyles></style><contents><textItem><dataSource><dataItemLabel refDataItem="ID Number"/></dataSource></textItem></contents></listColumnTitle><listColumnBody><style><defaultStyles><defaultStyle refStyle="lc"/></defaultStyles></style><contents><textItem><dataSource><dataItemValue refDataItem="ID Number"/></dataSource></textItem></contents></listColumnBody></listColumn><listColumn><listColumnTitle><style><defaultStyles><defaultStyle refStyle="lt"/></defaultStyles></style><contents><textItem><dataSource><dataItemLabel refDataItem="Full Name (Last, First)"/></dataSource></textItem></contents></listColumnTitle><listColumnBody><style><defaultStyles><defaultStyle refStyle="lc"/></defaultStyles></style><contents><textItem><dataSource><dataItemValue refDataItem="Full Name (Last, First)"/></dataSource></textItem></contents></listColumnBody></listColumn></listColumns><listGroups><listGroup refDataItem="Title Code"><sortList><sortItem refDataItem="Title Code" sortOrder="descending"/></sortList></listGroup><listGroup refDataItem="Profile Exists"/></listGroups><listOverallGroup><listFooter><listRows><listRow><rowCells><rowCell><contents><textItem><dataSource><staticValue>Overall</staticValue></dataSource></textItem><textItem><dataSource><staticValue> - </staticValue></dataSource></textItem><textItem><dataSource><staticValue>Count Distinct</staticValue></dataSource></textItem></contents><style><defaultStyles><defaultStyle refStyle="if"/></defaultStyles></style></rowCell><rowCell><contents/><style><defaultStyles><defaultStyle refStyle="if"/></defaultStyles></style></rowCell><rowCell><contents><textItem><dataSource><dataItemValue refDataItem="Count Distinct(ID Number)"/></dataSource></textItem></contents><style><defaultStyles><defaultStyle refStyle="is"/></defaultStyles></style></rowCell><rowCell colSpan="1"><contents/><style><defaultStyles><defaultStyle refStyle="if"/></defaultStyles></style></rowCell></rowCells></listRow></listRows></listFooter></listOverallGroup></list></contents>
						<style>
							<defaultStyles>
								<defaultStyle refStyle="pb"/>
							</defaultStyles>
						</style>
					</pageBody>
					<style>
						<defaultStyles>
							<defaultStyle refStyle="pg"/>
						</defaultStyles>
					</style>
				</page><page name="Suffix Name matches its Table.">
					<pageBody>
						<contents><list horizontalPagination="true" name="List11" refQuery="Query1">
								<noDataHandler>
									<contents>
										<block>
											<contents>
												<textItem>
													<dataSource>
														<staticValue>No Data Available</staticValue>
													</dataSource>
													<style>
														<CSS value="padding:10px 18px;"/>
													</style>
												</textItem>
											</contents>
										</block>
									</contents>
								</noDataHandler>
								<style>
									<CSS value="border-collapse:collapse"/>
									<defaultStyles>
										<defaultStyle refStyle="ls"/>
									</defaultStyles>
								</style>
								<listColumns><listColumn><listColumnTitle><style><defaultStyles><defaultStyle refStyle="lt"/></defaultStyles></style><contents><textItem><dataSource><dataItemLabel refDataItem="ID Number"/></dataSource></textItem></contents></listColumnTitle><listColumnBody><style><defaultStyles><defaultStyle refStyle="lc"/></defaultStyles></style><contents><textItem><dataSource><dataItemValue refDataItem="ID Number"/></dataSource></textItem></contents></listColumnBody></listColumn><listColumn><listColumnTitle><style><defaultStyles><defaultStyle refStyle="lt"/></defaultStyles></style><contents><textItem><dataSource><dataItemLabel refDataItem="Full Name (Last, First)"/></dataSource></textItem></contents></listColumnTitle><listColumnBody><style><defaultStyles><defaultStyle refStyle="lc"/></defaultStyles></style><contents><textItem><dataSource><dataItemValue refDataItem="Full Name (Last, First)"/></dataSource></textItem></contents></listColumnBody></listColumn><listColumn><listColumnTitle><style><defaultStyles><defaultStyle refStyle="lt"/></defaultStyles></style><contents><textItem><dataSource><dataItemLabel refDataItem="Name Suffix"/></dataSource></textItem></contents></listColumnTitle><listColumnBody><style><defaultStyles><defaultStyle refStyle="lc"/></defaultStyles></style><contents><textItem><dataSource><dataItemValue refDataItem="Name Suffix"/></dataSource></textItem></contents></listColumnBody></listColumn></listColumns></list></contents>
						<style>
							<defaultStyles>
								<defaultStyle refStyle="pb"/>
							</defaultStyles>
						</style>
					</pageBody>
					<style>
						<defaultStyles>
							<defaultStyle refStyle="pg"/>
						</defaultStyles>
					</style>
				</page></reportPages>
		</layout>
	</layouts>
	<XMLAttributes><XMLAttribute name="RS_CreateExtendedDataItems" value="true" output="no"/><XMLAttribute name="listSeparator" value="," output="no"/><XMLAttribute name="RS_modelModificationTime" value="2014-01-30T15:17:47.763Z" output="no"/></XMLAttributes><reportName>Data Cleanup</reportName></report>
